cli.py
setup.py
jsonselect/__init__.py
jsonselect/jsonselect.py
pyjsonselect.egg-info/PKG-INFO
pyjsonselect.egg-info/SOURCES.txt
pyjsonselect.egg-info/dependency_links.txt
pyjsonselect.egg-info/top_level.txt