Metadata-Version: 1.1
Name: pyjsonselect
Version: 0.2.1
Summary: Fully-compliant implementation of JSONSelect
Home-page: https://github.com/danvk/pyjsonselect/
Author: Dan Vanderkam
Author-email: danvdk@gmail.com
License: UNKNOWN
Keywords: css,json,jsonselect
Platform: UNKNOWN
Classifier: Development Status :: 4 - Beta
Classifier: Intended Audience :: Developers
Classifier: License :: OSI Approved :: Apache Software License
Classifier: Topic :: Utilities
Classifier: Topic :: Text Processing
